[
  {
    "id": "12fd6f83-3838-4642-92a1-257aefd68997",
    "name": "Sadie Ferry",
    "phone": "1-380-982-9144 x062",
    "email": "Milan17@gmail.com",
    "job": "Legacy Branding Assistant"
  },
  {
    "id": "70ce1e08-772e-47cf-8ad4-6ffe606c680c",
    "name": "Melba Quigley",
    "phone": "883-642-1991 x36381",
    "email": "Albin10@hotmail.com",
    "job": "Internal Intranet Administrator"
  },
  {
    "id": "6de97c1a-cd8f-4914-a72e-5761754d225b",
    "name": "Ruby Huel",
    "phone": "262.808.8112 x06759",
    "email": "Maximillian0@hotmail.com",
    "job": "Product Identity Associate"
  },
  {
    "id": "08a76d9a-84ae-46b0-a414-9426ea44a7b9",
    "name": "Kim Okuneva",
    "phone": "1-971-313-4389 x83052",
    "email": "Lempi_Hickle@yahoo.com",
    "job": "Customer Functionality Planner"
  },
  {
    "id": "4650104e-e7ec-47f8-a6bc-b8c27a5b7f65",
    "name": "Erika Christiansen",
    "phone": "1-269-946-0488 x4123",
    "email": "Helen.Hodkiewicz52@yahoo.com",
    "job": "Direct Configuration Executive"
  },
  {
    "id": "be088a8c-8081-4dd0-ba66-6790f03c4dde",
    "name": "Mrs. Patti Treutel",
    "phone": "(470) 294-7227 x354",
    "email": "Twila_Torphy@hotmail.com",
    "job": "Human Configuration Representative"
  },
  {
    "id": "bb83dabc-79e0-49b1-9843-b4ac300b2110",
    "name": "Myron Kunze",
    "phone": "877-839-6711",
    "email": "Stephon.Heathcote@gmail.com",
    "job": "Principal Creative Consultant"
  },
  {
    "id": "8b81d353-1777-48cf-9505-1c42f107d77d",
    "name": "Caleb Reilly",
    "phone": "1-500-824-5474 x963",
    "email": "Casandra32@yahoo.com",
    "job": "Global Group Liaison"
  },
  {
    "id": "18d1dfa4-3cae-49da-978c-7e57e3a47c21",
    "name": "Morris Medhurst",
    "phone": "1-758-415-5559 x6888",
    "email": "Erika61@gmail.com",
    "job": "International Functionality Consultant"
  },
  {
    "id": "bc720b73-1c76-46ba-bd69-3c107471ac79",
    "name": "Diana Murphy",
    "phone": "1-399-322-6732",
    "email": "Ellsworth_Pagac@yahoo.com",
    "job": "Internal Accountability Specialist"
  },
  {
    "id": "a934cc9d-c368-462f-9b9e-99c9219437d5",
    "name": "Melvin Brekke",
    "phone": "(909) 708-2874 x21163",
    "email": "Lurline13@gmail.com",
    "job": "National Data Producer"
  }
]